compares.py
compares-0.1.1.dist-info/DESCRIPTION.rst
compares-0.1.1.dist-info/METADATA
compares-0.1.1.dist-info/metadata.json
compares-0.1.1.dist-info/RECORD
compares-0.1.1.dist-info/top_level.txt
compares-0.1.1.dist-info/WHEEL
